injecty_config_servey_stub/__init__.py
servey_stub/__init__.py
servey_stub/__main__.py
servey_stub/errors.py
servey_stub/http_service_definition.py
servey_stub/lambda_service_definition.py
servey_stub/mock_service_definition.py
servey_stub/service_definition_abc.py
servey_stub/utils.py
servey_stub/templates/__init__.py
servey_stub/templates/http_utils.py
servey_stub/templates/lambda_utils.py
servey_stub/templates/mock_utils.py
servey_stub/templates/setup.txt
servey_stub/type_definition/__init__.py
servey_stub/type_definition/dataclass_definition.py
servey_stub/type_definition/dataclass_type_definition_factory.py
servey_stub/type_definition/enum_type_definition_factory.py
servey_stub/type_definition/field_definition.py
servey_stub/type_definition/forward_ref_definition_factory.py
servey_stub/type_definition/generic_type_definition_factory.py
servey_stub/type_definition/imports_definition.py
servey_stub/type_definition/primitive_type_definition_factory.py
servey_stub/type_definition/type_definition.py
servey_stub/type_definition/type_definition_context.py
servey_stub/type_definition/type_definition_factory_abc.py
servey_stub-0.0.10.dist-info/METADATA
servey_stub-0.0.10.dist-info/WHEEL
servey_stub-0.0.10.dist-info/top_level.txt
servey_stub-0.0.10.dist-info/RECORD
