Metadata-Version: 2.1
Name: servey-stub
Version: 0.0.10
Summary: A service stub generator for servey
Home-page: https://github.com/tofarr/servey-stub
Author: Tim O'Farrell
Author-email: tofarr@gmail.com
Classifier: Programming Language :: Python :: 3
Classifier: License :: OSI Approved :: MIT License
Classifier: Operating System :: OS Independent
Requires-Dist: injecty ~=0.0
Requires-Dist: servey ~=4.0
Provides-Extra: all
Requires-Dist: requests ~=2.31 ; extra == 'all'
Requires-Dist: pytest-cov ~=4.0 ; extra == 'all'
Requires-Dist: boto3 ~=1.26 ; extra == 'all'
Requires-Dist: pytest-xdist ~=3.2 ; extra == 'all'
Requires-Dist: black ~=23.3 ; extra == 'all'
Requires-Dist: pylint ~=3.0 ; extra == 'all'
Requires-Dist: pytest ~=7.2 ; extra == 'all'
Provides-Extra: dev
Requires-Dist: black ~=23.3 ; extra == 'dev'
Requires-Dist: boto3 ~=1.26 ; extra == 'dev'
Requires-Dist: requests ~=2.31 ; extra == 'dev'
Requires-Dist: pytest ~=7.2 ; extra == 'dev'
Requires-Dist: pytest-cov ~=4.0 ; extra == 'dev'
Requires-Dist: pytest-xdist ~=3.2 ; extra == 'dev'
Requires-Dist: pylint ~=3.0 ; extra == 'dev'
